pykoppu/__init__.py
pykoppu/biocompiler/__init__.py
pykoppu/biocompiler/compiler.py
pykoppu/biocompiler/isa.py
pykoppu/electrophysiology/__init__.py
pykoppu/electrophysiology/base.py
pykoppu/electrophysiology/cloud.py
pykoppu/electrophysiology/cpu.py
pykoppu/electrophysiology/gpu.py
pykoppu/electrophysiology/intan.py
pykoppu/oos/__init__.py
pykoppu/oos/process.py
pykoppu/oos/result.py
pykoppu/opu/__init__.py
pykoppu/opu/device.py
pykoppu/opu/kernel.py
pykoppu/opu/pobit.py
pykoppu/problems/__init__.py
pykoppu/problems/base.py
pykoppu/problems/energy/__init__.py
pykoppu/problems/energy/seismic.py
pykoppu/problems/energy/well_placement.py
pykoppu/problems/finance/__init__.py
pykoppu/problems/finance/portfolio.py
pykoppu/problems/graph/__init__.py
pykoppu/problems/graph/maxcut.py
pykoppu/problems/logistics/__init__.py
pykoppu/problems/logistics/knapsack.py
pykoppu/problems/logistics/tsp.py
pykoppu/problems/math/__init__.py
pykoppu/problems/math/factorization.py
pykoppu/problems/math/sat3.py
pykoppu-0.2.34a0.dist-info/licenses/LICENSE
pykoppu-0.2.34a0.dist-info/METADATA
pykoppu-0.2.34a0.dist-info/WHEEL
pykoppu-0.2.34a0.dist-info/top_level.txt
pykoppu-0.2.34a0.dist-info/RECORD
