Metadata-Version: 2.4
Name: pykoppu
Version: 0.2.34a0
Summary: SDK for KOPPU (K-dimensional Organoid Probabilistic Processing Unit)
Home-page: https://koppu.io
Author: KOPPU Team
Author-email: KOPPU Team <contact@koppu.io>
License: MIT
Project-URL: Homepage, https://koppu.io
Project-URL: Repository, https://github.com/koppu/pykoppu
Project-URL: Bug Tracker, https://github.com/koppu/pykoppu/issues
Keywords: organoid computing,neuromorphic,optimization,pubo,brian2
Classifier: Programming Language :: Python :: 3
Classifier: License :: OSI Approved :: MIT License
Classifier: Operating System :: OS Independent
Classifier: Development Status :: 3 - Alpha
Classifier: Intended Audience :: Science/Research
Classifier: Topic :: Scientific/Engineering :: Bio-Informatics
Requires-Python: >=3.8
License-File: LICENSE
Requires-Dist: brian2>=2.5
Requires-Dist: networkx
Requires-Dist: numpy
Requires-Dist: scipy
Provides-Extra: doc
Requires-Dist: mkdocs-material; extra == "doc"
Requires-Dist: mkdocstrings[python]; extra == "doc"
Dynamic: author
Dynamic: home-page
Dynamic: license-file
Dynamic: requires-python
